swydd-0.1.0.dist-info/METADATA
swydd-0.1.0.dist-info/WHEEL
swydd-0.1.0.dist-info/licenses/LICENSE
swydd/__init__.py
swydd-0.1.0.dist-info/RECORD
