Metadata-Version: 2.1
Name: swydd
Version: 0.1.0
Summary: swydd will yield desired deliverables
Author-Email: Daylin Morgan <daylinmorgan@gmail.com>
License: MIT
Requires-Python: >=3.9
